{"stats":{"total":918,"passed":918},"status":"passed","newTests":[],"flakyTests":[],"retryTests":[],"checks":[],"name":"Allure Report Allure Report","duration":178031,"createdAt":1784640089364,"plugin":"Awesome","meta":{"reportId":"dca98181-e5da-4a55-bb48-beabcbbaa92b","singleFile":false,"withTestResultsLinks":true},"pluginId":"awesome","pullRequestHref":"https://github.com/koreyba/EverFreeNote/pull/153","jobHref":"https://github.com/koreyba/EverFreeNote/actions/runs/29833671838","href":"awesome/"}