{"stats":{"total":1556,"passed":1555,"skipped":1},"status":"passed","newTests":[],"flakyTests":[],"retryTests":[],"checks":[],"name":"Allure Report Allure Report","duration":160470,"createdAt":1783716253465,"plugin":"Awesome","meta":{"reportId":"17ff0bef-183d-425a-aa99-1a49fe56923c","singleFile":false,"withTestResultsLinks":true},"pluginId":"awesome","pullRequestHref":"https://github.com/koreyba/EverFreeNote/pull/143","jobHref":"https://github.com/koreyba/EverFreeNote/actions/runs/29121971216","href":"awesome/"}