{"stats":{"total":885,"passed":885},"status":"passed","newTests":[],"flakyTests":[],"retryTests":[],"checks":[],"name":"Allure Report Allure Report","duration":38343,"createdAt":1784556745889,"plugin":"Awesome","meta":{"reportId":"8c75e327-09a1-4a35-ba1e-4fb90e665a30","singleFile":false,"withTestResultsLinks":true},"pluginId":"awesome","pullRequestHref":"https://github.com/koreyba/EverFreeNote/pull/153","jobHref":"https://github.com/koreyba/EverFreeNote/actions/runs/29749479053","href":"awesome/"}