{"stats":{"total":2215,"passed":2215},"status":"passed","newTests":[],"flakyTests":[],"retryTests":[],"checks":[],"name":"Allure Report Allure Report","duration":304335,"createdAt":1784808232552,"plugin":"Awesome","meta":{"reportId":"c3f153f5-67c8-46a0-85ea-13172c40d0f8","singleFile":false,"withTestResultsLinks":true},"pluginId":"awesome","pullRequestHref":"https://github.com/koreyba/EverFreeNote/pull/164","jobHref":"https://github.com/koreyba/EverFreeNote/actions/runs/30004610261","href":"awesome/"}