{"stats":{"total":1516,"passed":1516},"status":"passed","newTests":[],"flakyTests":[],"retryTests":[],"checks":[],"name":"Allure Report Allure Report","duration":51169,"createdAt":1784796692361,"plugin":"Awesome","meta":{"reportId":"2cb45366-05f5-46f6-9470-e93bdf1041b6","singleFile":false,"withTestResultsLinks":true},"pluginId":"awesome","pullRequestHref":"https://github.com/koreyba/EverFreeNote/pull/162","jobHref":"https://github.com/koreyba/EverFreeNote/actions/runs/29992605393","href":"awesome/"}