{"stats":{"total":911,"passed":911,"retries":1},"status":"passed","newTests":[],"flakyTests":[],"retryTests":[],"checks":[],"name":"Allure Report Allure Report","duration":171782,"createdAt":1784566105606,"plugin":"Awesome","meta":{"reportId":"28ab2953-c3f9-409b-acb3-b874ba5259c6","singleFile":false,"withTestResultsLinks":true},"pluginId":"awesome","pullRequestHref":"https://github.com/koreyba/EverFreeNote/pull/153","jobHref":"https://github.com/koreyba/EverFreeNote/actions/runs/29760768345","href":"awesome/"}