{"uuid":"b24990a3-34ca-460d-90be-f8c539636410","name":"E2E Allure Report – Pull request #121","timestamp":1778267654398,"knownTestCaseIds":["991cf52650938f01e826928b62b1307c","01eca9fd35f1f07abcb9693db2e359de","7c24e6741fda6a2c0500d441cfa4b97a","d1b379516c56a50f768e13fde64c1edc","750b4689ac15807611d743fe978fd68c"],"testResults":{"991cf52650938f01e826928b62b1307c.5bd835b0d6b1d4ada3b9f0db936e82c8":{"id":"1442b90c808e52f8dd2fc509c95bb79b","name":"bulk delete selected notes","fullName":"notes.bulk-delete.spec.ts:37:7","environment":"default","status":"passed","start":1778267472880,"stop":1778267481180,"duration":8300,"labels":[{"name":"language","value":"javascript"},{"name":"framework","value":"playwright"},{"name":"package","value":"notes.bulk-delete.spec.ts"},{"name":"titlePath","value":" > chromium > notes.bulk-delete.spec.ts > notes bulk delete"},{"name":"host","value":"runnervmeorf1"},{"name":"thread","value":"pid-5591-worker-0"},{"name":"parentSuite","value":"chromium"},{"name":"suite","value":"e2e"},{"name":"subSuite","value":"notes bulk delete"},{"name":"family","value":"e2e"},{"name":"surface","value":"web"},{"name":"layer","value":"e2e"},{"name":"workflow","value":"e2e-tests"}],"url":"","historyId":"991cf52650938f01e826928b62b1307c.5bd835b0d6b1d4ada3b9f0db936e82c8","reportLinks":[]},"01eca9fd35f1f07abcb9693db2e359de.84e28e814b821ed013329cc8dbc467e0":{"id":"4bc48363ec2ec97621992612a1370c2e","name":"export and import selected notes from enex file","fullName":"notes.export-import.spec.ts:50:7","environment":"default","status":"passed","start":1778267555453,"stop":1778267575336,"duration":19883,"labels":[{"name":"language","value":"javascript"},{"name":"framework","value":"playwright"},{"name":"package","value":"notes.export-import.spec.ts"},{"name":"titlePath","value":" > webkit > notes.export-import.spec.ts > notes export/import"},{"name":"host","value":"runnervmeorf1"},{"name":"thread","value":"pid-5591-worker-0"},{"name":"parentSuite","value":"webkit"},{"name":"suite","value":"e2e"},{"name":"subSuite","value":"notes export/import"},{"name":"family","value":"e2e"},{"name":"surface","value":"web"},{"name":"layer","value":"e2e"},{"name":"workflow","value":"e2e-tests"}],"url":"","historyId":"01eca9fd35f1f07abcb9693db2e359de.84e28e814b821ed013329cc8dbc467e0","reportLinks":[]},"7c24e6741fda6a2c0500d441cfa4b97a.84e28e814b821ed013329cc8dbc467e0":{"id":"cf2b3d1a64a46f222f10a9d847177212","name":"create, read, and delete a note","fullName":"notes.spec.ts:26:7","environment":"default","status":"passed","start":1778267587366,"stop":1778267591230,"duration":3864,"labels":[{"name":"language","value":"javascript"},{"name":"framework","value":"playwright"},{"name":"package","value":"notes.spec.ts"},{"name":"titlePath","value":" > webkit > notes.spec.ts > notes crud"},{"name":"host","value":"runnervmeorf1"},{"name":"thread","value":"pid-5591-worker-0"},{"name":"parentSuite","value":"webkit"},{"name":"suite","value":"e2e"},{"name":"subSuite","value":"notes crud"},{"name":"family","value":"e2e"},{"name":"surface","value":"web"},{"name":"layer","value":"e2e"},{"name":"workflow","value":"e2e-tests"}],"url":"","historyId":"7c24e6741fda6a2c0500d441cfa4b97a.84e28e814b821ed013329cc8dbc467e0","reportLinks":[]},"991cf52650938f01e826928b62b1307c.84e28e814b821ed013329cc8dbc467e0":{"id":"58e00b8a701019eb1d0abc44cde5fee2","name":"bulk delete selected notes","fullName":"notes.bulk-delete.spec.ts:37:7","environment":"default","status":"passed","start":1778267543479,"stop":1778267554888,"duration":11409,"labels":[{"name":"language","value":"javascript"},{"name":"framework","value":"playwright"},{"name":"package","value":"notes.bulk-delete.spec.ts"},{"name":"titlePath","value":" > webkit > notes.bulk-delete.spec.ts > notes bulk delete"},{"name":"host","value":"runnervmeorf1"},{"name":"thread","value":"pid-5591-worker-0"},{"name":"parentSuite","value":"webkit"},{"name":"suite","value":"e2e"},{"name":"subSuite","value":"notes bulk delete"},{"name":"family","value":"e2e"},{"name":"surface","value":"web"},{"name":"layer","value":"e2e"},{"name":"workflow","value":"e2e-tests"}],"url":"","historyId":"991cf52650938f01e826928b62b1307c.84e28e814b821ed013329cc8dbc467e0","reportLinks":[]},"01eca9fd35f1f07abcb9693db2e359de.5bd835b0d6b1d4ada3b9f0db936e82c8":{"id":"4465070b85585f4306893da2023c1242","name":"export and import selected notes from enex file","fullName":"notes.export-import.spec.ts:50:7","environment":"default","status":"passed","start":1778267481278,"stop":1778267496092,"duration":14814,"labels":[{"name":"language","value":"javascript"},{"name":"framework","value":"playwright"},{"name":"package","value":"notes.export-import.spec.ts"},{"name":"titlePath","value":" > chromium > notes.export-import.spec.ts > notes export/import"},{"name":"host","value":"runnervmeorf1"},{"name":"thread","value":"pid-5591-worker-0"},{"name":"parentSuite","value":"chromium"},{"name":"suite","value":"e2e"},{"name":"subSuite","value":"notes export/import"},{"name":"family","value":"e2e"},{"name":"surface","value":"web"},{"name":"layer","value":"e2e"},{"name":"workflow","value":"e2e-tests"}],"url":"","historyId":"01eca9fd35f1f07abcb9693db2e359de.5bd835b0d6b1d4ada3b9f0db936e82c8","reportLinks":[]},"d1b379516c56a50f768e13fde64c1edc.84e28e814b821ed013329cc8dbc467e0":{"id":"c46bab3625edbb61fe3cf8a220bc2002","name":"long query search shows full-text results and supports tag filtering","fullName":"notes.search.spec.ts:71:7","environment":"default","status":"passed","start":1778267575379,"stop":1778267582158,"duration":6779,"labels":[{"name":"language","value":"javascript"},{"name":"framework","value":"playwright"},{"name":"package","value":"notes.search.spec.ts"},{"name":"titlePath","value":" > webkit > notes.search.spec.ts > notes search"},{"name":"host","value":"runnervmeorf1"},{"name":"thread","value":"pid-5591-worker-0"},{"name":"parentSuite","value":"webkit"},{"name":"suite","value":"e2e"},{"name":"subSuite","value":"notes search"},{"name":"family","value":"e2e"},{"name":"surface","value":"web"},{"name":"layer","value":"e2e"},{"name":"workflow","value":"e2e-tests"}],"url":"","historyId":"d1b379516c56a50f768e13fde64c1edc.84e28e814b821ed013329cc8dbc467e0","reportLinks":[]},"750b4689ac15807611d743fe978fd68c.84e28e814b821ed013329cc8dbc467e0":{"id":"98936b26c4eebca38c6d15d24dd2ff72","name":"shared note opens for signed-out visitors","fullName":"notes.share.spec.ts:45:7","environment":"default","status":"passed","start":1778267582183,"stop":1778267587340,"duration":5157,"labels":[{"name":"language","value":"javascript"},{"name":"framework","value":"playwright"},{"name":"package","value":"notes.share.spec.ts"},{"name":"titlePath","value":" > webkit > notes.share.spec.ts > notes sharing"},{"name":"host","value":"runnervmeorf1"},{"name":"thread","value":"pid-5591-worker-0"},{"name":"parentSuite","value":"webkit"},{"name":"suite","value":"e2e"},{"name":"subSuite","value":"notes sharing"},{"name":"family","value":"e2e"},{"name":"surface","value":"web"},{"name":"layer","value":"e2e"},{"name":"workflow","value":"e2e-tests"}],"url":"","historyId":"750b4689ac15807611d743fe978fd68c.84e28e814b821ed013329cc8dbc467e0","reportLinks":[]},"750b4689ac15807611d743fe978fd68c.b444eb0fbe6390c71e68b51dd25701fc":{"id":"b910e58a861d91fa341e9bcbf86280be","name":"shared note opens for signed-out visitors","fullName":"notes.share.spec.ts:45:7","environment":"default","status":"passed","start":1778267535005,"stop":1778267539283,"duration":4278,"labels":[{"name":"language","value":"javascript"},{"name":"framework","value":"playwright"},{"name":"package","value":"notes.share.spec.ts"},{"name":"titlePath","value":" > firefox > notes.share.spec.ts > notes sharing"},{"name":"host","value":"runnervmeorf1"},{"name":"thread","value":"pid-5591-worker-0"},{"name":"parentSuite","value":"firefox"},{"name":"suite","value":"e2e"},{"name":"subSuite","value":"notes sharing"},{"name":"family","value":"e2e"},{"name":"surface","value":"web"},{"name":"layer","value":"e2e"},{"name":"workflow","value":"e2e-tests"}],"url":"","historyId":"750b4689ac15807611d743fe978fd68c.b444eb0fbe6390c71e68b51dd25701fc","reportLinks":[]},"d1b379516c56a50f768e13fde64c1edc.b444eb0fbe6390c71e68b51dd25701fc":{"id":"15e0fe83192b7e461073dcd119e0f6f7","name":"long query search shows full-text results and supports tag filtering","fullName":"notes.search.spec.ts:71:7","environment":"default","status":"passed","start":1778267529029,"stop":1778267534976,"duration":5947,"labels":[{"name":"language","value":"javascript"},{"name":"framework","value":"playwright"},{"name":"package","value":"notes.search.spec.ts"},{"name":"titlePath","value":" > firefox > notes.search.spec.ts > notes search"},{"name":"host","value":"runnervmeorf1"},{"name":"thread","value":"pid-5591-worker-0"},{"name":"parentSuite","value":"firefox"},{"name":"suite","value":"e2e"},{"name":"subSuite","value":"notes search"},{"name":"family","value":"e2e"},{"name":"surface","value":"web"},{"name":"layer","value":"e2e"},{"name":"workflow","value":"e2e-tests"}],"url":"","historyId":"d1b379516c56a50f768e13fde64c1edc.b444eb0fbe6390c71e68b51dd25701fc","reportLinks":[]},"7c24e6741fda6a2c0500d441cfa4b97a.5bd835b0d6b1d4ada3b9f0db936e82c8":{"id":"4f43fd1e8b4f5e960a0e3255a69a1900","name":"create, read, and delete a note","fullName":"notes.spec.ts:26:7","environment":"default","status":"passed","start":1778267506057,"stop":1778267508209,"duration":2152,"labels":[{"name":"language","value":"javascript"},{"name":"framework","value":"playwright"},{"name":"package","value":"notes.spec.ts"},{"name":"titlePath","value":" > chromium > notes.spec.ts > notes crud"},{"name":"host","value":"runnervmeorf1"},{"name":"thread","value":"pid-5591-worker-0"},{"name":"parentSuite","value":"chromium"},{"name":"suite","value":"e2e"},{"name":"subSuite","value":"notes crud"},{"name":"family","value":"e2e"},{"name":"surface","value":"web"},{"name":"layer","value":"e2e"},{"name":"workflow","value":"e2e-tests"}],"url":"","historyId":"7c24e6741fda6a2c0500d441cfa4b97a.5bd835b0d6b1d4ada3b9f0db936e82c8","reportLinks":[]},"d1b379516c56a50f768e13fde64c1edc.5bd835b0d6b1d4ada3b9f0db936e82c8":{"id":"d0eee13fc9ca837ec22df7324fd452cf","name":"long query search shows full-text results and supports tag filtering","fullName":"notes.search.spec.ts:71:7","environment":"default","status":"passed","start":1778267496129,"stop":1778267501827,"duration":5698,"labels":[{"name":"language","value":"javascript"},{"name":"framework","value":"playwright"},{"name":"package","value":"notes.search.spec.ts"},{"name":"titlePath","value":" > chromium > notes.search.spec.ts > notes search"},{"name":"host","value":"runnervmeorf1"},{"name":"thread","value":"pid-5591-worker-0"},{"name":"parentSuite","value":"chromium"},{"name":"suite","value":"e2e"},{"name":"subSuite","value":"notes search"},{"name":"family","value":"e2e"},{"name":"surface","value":"web"},{"name":"layer","value":"e2e"},{"name":"workflow","value":"e2e-tests"}],"url":"","historyId":"d1b379516c56a50f768e13fde64c1edc.5bd835b0d6b1d4ada3b9f0db936e82c8","reportLinks":[]},"7c24e6741fda6a2c0500d441cfa4b97a.b444eb0fbe6390c71e68b51dd25701fc":{"id":"5ebfc7c6e65eba77cd694be1027dc891","name":"create, read, and delete a note","fullName":"notes.spec.ts:26:7","environment":"default","status":"passed","start":1778267539303,"stop":1778267541890,"duration":2587,"labels":[{"name":"language","value":"javascript"},{"name":"framework","value":"playwright"},{"name":"package","value":"notes.spec.ts"},{"name":"titlePath","value":" > firefox > notes.spec.ts > notes crud"},{"name":"host","value":"runnervmeorf1"},{"name":"thread","value":"pid-5591-worker-0"},{"name":"parentSuite","value":"firefox"},{"name":"suite","value":"e2e"},{"name":"subSuite","value":"notes crud"},{"name":"family","value":"e2e"},{"name":"surface","value":"web"},{"name":"layer","value":"e2e"},{"name":"workflow","value":"e2e-tests"}],"url":"","historyId":"7c24e6741fda6a2c0500d441cfa4b97a.b444eb0fbe6390c71e68b51dd25701fc","reportLinks":[]},"991cf52650938f01e826928b62b1307c.b444eb0fbe6390c71e68b51dd25701fc":{"id":"53d8e8bb65a156a998bfccf073edd19d","name":"bulk delete selected notes","fullName":"notes.bulk-delete.spec.ts:37:7","environment":"default","status":"passed","start":1778267509239,"stop":1778267515513,"duration":6274,"labels":[{"name":"language","value":"javascript"},{"name":"framework","value":"playwright"},{"name":"package","value":"notes.bulk-delete.spec.ts"},{"name":"titlePath","value":" > firefox > notes.bulk-delete.spec.ts > notes bulk delete"},{"name":"host","value":"runnervmeorf1"},{"name":"thread","value":"pid-5591-worker-0"},{"name":"parentSuite","value":"firefox"},{"name":"suite","value":"e2e"},{"name":"subSuite","value":"notes bulk delete"},{"name":"family","value":"e2e"},{"name":"surface","value":"web"},{"name":"layer","value":"e2e"},{"name":"workflow","value":"e2e-tests"}],"url":"","historyId":"991cf52650938f01e826928b62b1307c.b444eb0fbe6390c71e68b51dd25701fc","reportLinks":[]},"01eca9fd35f1f07abcb9693db2e359de.b444eb0fbe6390c71e68b51dd25701fc":{"id":"c7a1aba2ba52ec9f102d6c5eca676ecd","name":"export and import selected notes from enex file","fullName":"notes.export-import.spec.ts:50:7","environment":"default","status":"passed","start":1778267515911,"stop":1778267528987,"duration":13076,"labels":[{"name":"language","value":"javascript"},{"name":"framework","value":"playwright"},{"name":"package","value":"notes.export-import.spec.ts"},{"name":"titlePath","value":" > firefox > notes.export-import.spec.ts > notes export/import"},{"name":"host","value":"runnervmeorf1"},{"name":"thread","value":"pid-5591-worker-0"},{"name":"parentSuite","value":"firefox"},{"name":"suite","value":"e2e"},{"name":"subSuite","value":"notes export/import"},{"name":"family","value":"e2e"},{"name":"surface","value":"web"},{"name":"layer","value":"e2e"},{"name":"workflow","value":"e2e-tests"}],"url":"","historyId":"01eca9fd35f1f07abcb9693db2e359de.b444eb0fbe6390c71e68b51dd25701fc","reportLinks":[]},"750b4689ac15807611d743fe978fd68c.5bd835b0d6b1d4ada3b9f0db936e82c8":{"id":"6f353cf2b98e1cf2ba4825c2c896cda7","name":"shared note opens for signed-out visitors","fullName":"notes.share.spec.ts:45:7","environment":"default","status":"passed","start":1778267501850,"stop":1778267506038,"duration":4188,"labels":[{"name":"language","value":"javascript"},{"name":"framework","value":"playwright"},{"name":"package","value":"notes.share.spec.ts"},{"name":"titlePath","value":" > chromium > notes.share.spec.ts > notes sharing"},{"name":"host","value":"runnervmeorf1"},{"name":"thread","value":"pid-5591-worker-0"},{"name":"parentSuite","value":"chromium"},{"name":"suite","value":"e2e"},{"name":"subSuite","value":"notes sharing"},{"name":"family","value":"e2e"},{"name":"surface","value":"web"},{"name":"layer","value":"e2e"},{"name":"workflow","value":"e2e-tests"}],"url":"","historyId":"750b4689ac15807611d743fe978fd68c.5bd835b0d6b1d4ada3b9f0db936e82c8","reportLinks":[]}},"metrics":{},"url":""}