{"stats":{"total":905,"passed":905,"retries":1},"status":"passed","newTests":[],"flakyTests":[],"retryTests":[],"checks":[],"name":"Allure Report Allure Report","duration":195406,"createdAt":1784300774221,"plugin":"Awesome","meta":{"reportId":"d88015e4-c724-4d5a-a40b-61f24762b485","singleFile":false,"withTestResultsLinks":true},"pluginId":"awesome","pullRequestHref":"https://github.com/koreyba/EverFreeNote/pull/146","jobHref":"https://github.com/koreyba/EverFreeNote/actions/runs/29590306239","href":"awesome/"}